CombinatorialProbability/__init__.py
CombinatorialProbability/fileio.py
CombinatorialProbability/folder.py
CombinatorialProbability/combinatorics/CombinatorialSequence.py
CombinatorialProbability/combinatorics/CombinatorialStructure.py
CombinatorialProbability/combinatorics/__init__.py
CombinatorialProbability/integer_partition/__init__.py
CombinatorialProbability/integer_partition/_fit.py
CombinatorialProbability/integer_partition/_iterator_methods.py
CombinatorialProbability/integer_partition/_make_table.py
CombinatorialProbability/integer_partition/_partition_function.py
CombinatorialProbability/integer_partition/_sampling.py
CombinatorialProbability/integer_partition/_transforms.py
CombinatorialProbability/pdc/__init__.py
CombinatorialProbability/probability/__init__.py
CombinatorialProbability-0.0.3.dist-info/LICENCE
CombinatorialProbability-0.0.3.dist-info/METADATA
CombinatorialProbability-0.0.3.dist-info/WHEEL
CombinatorialProbability-0.0.3.dist-info/top_level.txt
CombinatorialProbability-0.0.3.dist-info/RECORD
