Metadata-Version: 2.1
Name: CombinatorialProbability
Version: 0.0.3
Summary: A POC for a combinatorial probability library using integer partitions as one example
Home-page: https://github.com/StephenDeSalvo/CombinatorialProbability
Author: Stephen DeSalvo
Author-email: stephendesalvo@gmail.com
License: Creative Commons Attribution-Noncommercial-Share Alike license
Platform: UNKNOWN
Classifier: Programming Language :: Python :: 3
Classifier: License :: OSI Approved :: MIT License
Classifier: Operating System :: OS Independent
Requires-Python: >=3.6
